{
  "id": 192,
  "is_start": false,
  "type": 0,
  "name": "Успокоение",
  "description": "Валерий Палыч потер лысину: «Так я, можно сказать, страховой случай сам для себя устроил? Герой-спасатель собственных денег?»",
  "image": "dzen",
  "properties_yes": {
    "text": "Ооооооммммм...",
    "pos": {"id_next": 226, "moves_next": 1, "chance": 0.5, "properties": {}},
    "neg": {"id_next": 226, "moves_next": 1, "chance": 0.5, "properties": {}},
    "neu": {"id_next": 226, "moves_next": 1, "chance": 0, "properties": {}}
  },
  "properties_no": {
    "text": "Вот оно счастье!",
    "pos": {"id_next": 226, "moves_next": 1, "chance": 1, "properties": {}},
    "neg": {"id_next": 226, "moves_next": 1, "chance": 0, "properties": {}},
    "neu": {"id_next": 226, "moves_next": 1, "chance": 0, "properties": {}}
  }
}